adb_unicode_keyboard/README.MD
adb_unicode_keyboard/__init__.py
adb_unicode_keyboard/requirements.txt
adb_unicode_keyboard/thirdparty.json
adb_unicode_keyboard-0.12.dist-info/LICENSE.rst
adb_unicode_keyboard-0.12.dist-info/METADATA
adb_unicode_keyboard-0.12.dist-info/WHEEL
adb_unicode_keyboard-0.12.dist-info/top_level.txt
adb_unicode_keyboard-0.12.dist-info/RECORD
