Metadata-Version: 2.1
Name: adb-unicode-keyboard
Version: 0.12
Summary: Send any Unicode character to your Android device
Home-page: https://github.com/hansalemaos/adb_unicode_keyboard
Author: Johannes Fischer
Author-email: aulasparticularesdealemaosp@gmail.com
License: MIT
Keywords: adb,android,unicode,keyboard
Classifier: Development Status :: 4 - Beta
Classifier: Programming Language :: Python :: 3 :: Only
Classifier: Programming Language :: Python :: 3.10
Classifier: Topic :: Software Development :: Libraries :: Python Modules
Classifier: Topic :: Utilities
License-File: LICENSE.rst
Requires-Dist: flexible-partial
Requires-Dist: keyboard
Requires-Dist: psutil
Requires-Dist: regex
Requires-Dist: requests
